pgb/__init__.py
pgb/pgb.py
pgb-0.0.1.dist-info/LICENSE
pgb-0.0.1.dist-info/METADATA
pgb-0.0.1.dist-info/WHEEL
pgb-0.0.1.dist-info/entry_points.txt
pgb-0.0.1.dist-info/top_level.txt
pgb-0.0.1.dist-info/RECORD
